ctlogging/__init__.py
ctlogging/config.py
ctlogging/context.py
ctlogging/filters.py
ctlogging/handlers.py
LICENSE
README.md
ctlogging-0.1.3.dist-info/LICENSE
ctlogging-0.1.3.dist-info/WHEEL
ctlogging-0.1.3.dist-info/METADATA
ctlogging-0.1.3.dist-info/RECORD
