Metadata-Version: 2.1
Name: ctlogging
Version: 0.1.3
Summary: Wrapper of Logging module for handling database and middlerware scenarios
Home-page: https://github.com/rohitchoudhary19398/ctlogging
License: MIT
Keywords: logging,uuid,middleware,dbhandler,corelationid
Author: Rohit Choudhary
Author-email: rohitchoudhary19398@gmail.com
Requires-Python: >=3.7,<4.0
Classifier: License :: OSI Approved :: MIT License
Classifier: Programming Language :: Python :: 3
Classifier: Programming Language :: Python :: 3.10
Classifier: Programming Language :: Python :: 3.7
Classifier: Programming Language :: Python :: 3.8
Classifier: Programming Language :: Python :: 3.9
Project-URL: Repository, https://github.com/rohitchoudhary19398/ctlogging
